hoopoe/Hoopoe.py
hoopoe/__init__.py
hoopoe/constants.py
hoopoe/utils.py
hoopoe_python-0.0.7.dist-info/LICENSE
hoopoe_python-0.0.7.dist-info/METADATA
hoopoe_python-0.0.7.dist-info/WHEEL
hoopoe_python-0.0.7.dist-info/entry_points.txt
hoopoe_python-0.0.7.dist-info/top_level.txt
hoopoe_python-0.0.7.dist-info/RECORD
