Metadata-Version: 2.1
Name: hoopoe-python
Version: 0.0.7
Summary: Python SDK for Hoopoe
Home-page: https://github.com/thevahidal/hoopoe-python
Author: Vahid Al
Author-email: thevahidal@gmail.com
License: MIT
Platform: UNKNOWN
Classifier: License :: OSI Approved :: MIT License
Classifier: Programming Language :: Python :: 3
Classifier: Programming Language :: Python :: 3.7
Requires-Dist: requests
Provides-Extra: dev
Requires-Dist: decouple ; extra == 'dev'
